animedata/__init__.py
animedata/common/__init__.py
animedata/common/dict_checking.py
animedata/common/lib_interactions.py
animedata/common/metadata.py
animedata/common/saving_process.py
animedata/resources/animedata_source.json
animedata/tests/__init__.py
animedata/tests/test_dict_checking.py
animedata/tests/test_lib_interaction.py
animedata-0.3.9.dist-info/METADATA
animedata-0.3.9.dist-info/WHEEL
animedata-0.3.9.dist-info/licenses/LICENSE
animedata-0.3.9.dist-info/RECORD
