Metadata-Version: 2.1
Name: animedata
Version: 0.3.9
Summary: Open-source library containing package about animes/series and including a built-in utility.
Project-URL: Github, https://github.com/swarthur/animedata
Project-URL: Bug, https://github.com/swarthur/animedata/issues
Author: swarthur
License-Expression: MIT
License-File: LICENSE
Classifier: License :: OSI Approved :: MIT License
Classifier: Operating System :: OS Independent
Classifier: Programming Language :: Python :: 3
Requires-Python: >=3.11
